gcs_pypi/__init__.py
gcs_pypi/__main__.py
gcs_pypi/exceptions.py
gcs_pypi/package.py
gcs_pypi/storage.py
gcs_pypi/templates/index.html.j2
gcs_pypi-0.1.111.dist-info/LICENSE
gcs_pypi-0.1.111.dist-info/METADATA
gcs_pypi-0.1.111.dist-info/WHEEL
gcs_pypi-0.1.111.dist-info/entry_points.txt
gcs_pypi-0.1.111.dist-info/top_level.txt
gcs_pypi-0.1.111.dist-info/RECORD
