Metadata-Version: 2.1
Name: gcs-pypi
Version: 0.1.111
Summary: CLI for creating a Python Package Repository in a GCS bucket
Home-page: UNKNOWN
Author: Tonye Jack
Author-email: jtonye@ymail.com
License: UNKNOWN
Platform: UNKNOWN
Requires-Python: !=3.0.*,!=3.1.*,!=3.2.*,!=3.3.*,!=3.4.*,<4.0,>=2.7
Requires-Dist: google-api-core (==1.*,>=1.17.0)
Requires-Dist: google-cloud-core (==1.*,>=1.3.0)
Requires-Dist: google-cloud-storage (==1.*,>=1.28.0)
Requires-Dist: jinja2 (==2.*,>=2.10.1)
Requires-Dist: wheel (==0.*,>=0.33.6)
Requires-Dist: futures (==3.*,>=3.3.0) ; python_version == "2.7.*" and python_version >= "2.7.0"
Provides-Extra: dev
Requires-Dist: bumpversion (==0.5.3) ; extra == 'dev'
Requires-Dist: flake8 (==3.*,>=3.7.8) ; extra == 'dev'
Requires-Dist: ipdb (==0.*,>=0.13.2) ; extra == 'dev'
Requires-Dist: isort (==4.*,>=4.3.21) ; extra == 'dev'
Requires-Dist: mock (==3.0.5) ; extra == 'dev'
Requires-Dist: pytest (>=4.6.5) ; extra == 'dev'
Requires-Dist: pytest-cov (==2.*,>=2.7.1) ; extra == 'dev'
Requires-Dist: black (==19.*,>=19.3.0.b0) ; (python_version == "3.*" and python_version >= "3.6.0") and extra == 'dev'
Requires-Dist: dephell (==0.*,>=0.8.3) ; (python_version == "3.*" and python_version >= "3.6.0") and extra == 'dev'
